{
  "Name": "EquipParamProtector",
  "Entries": [
    {
      "ID": 1000,
      "Entries": [
        ""
      ]
    },
    {
      "ID": 1100,
      "Entries": [
        ""
      ]
    },
    {
      "ID": 1200,
      "Entries": [
        ""
      ]
    },
    {
      "ID": 1300,
      "Entries": [
        ""
      ]
    },
    {
      "ID": 1400,
      "Entries": [
        ""
      ]
    },
    {
      "ID": 1500,
      "Entries": [
        ""
      ]
    },
    {
      "ID": 1600,
      "Entries": [
        ""
      ]
    },
    {
      "ID": 1700,
      "Entries": [
        ""
      ]
    },
    {
      "ID": 1800,
      "Entries": [
        ""
      ]
    },
    {
      "ID": 1900,
      "Entries": [
        ""
      ]
    },
    {
      "ID": 2000,
      "Entries": [
        ""
      ]
    },
    {
      "ID": 2100,
      "Entries": [
        ""
      ]
    },
    {
      "ID": 2200,
      "Entries": [
        ""
      ]
    },
    {
      "ID": 2300,
      "Entries": [
        ""
      ]
    },
    {
      "ID": 2400,
      "Entries": [
        ""
      ]
    },
    {
      "ID": 2500,
      "Entries": [
        ""
      ]
    },
    {
      "ID": 2600,
      "Entries": [
        ""
      ]
    },
    {
      "ID": 2700,
      "Entries": [
        ""
      ]
    },
    {
      "ID": 2800,
      "Entries": [
        ""
      ]
    },
    {
      "ID": 2900,
      "Entries": [
        ""
      ]
    },
    {
      "ID": 3000,
      "Entries": [
        ""
      ]
    },
    {
      "ID": 3100,
      "Entries": [
        ""
      ]
    },
    {
      "ID": 3200,
      "Entries": [
        ""
      ]
    },
    {
      "ID": 3300,
      "Entries": [
        ""
      ]
    },
    {
      "ID": 3400,
      "Entries": [
        ""
      ]
    },
    {
      "ID": 3500,
      "Entries": [
        ""
      ]
    },
    {
      "ID": 3600,
      "Entries": [
        ""
      ]
    },
    {
      "ID": 3700,
      "Entries": [
        ""
      ]
    },
    {
      "ID": 3800,
      "Entries": [
        ""
      ]
    },
    {
      "ID": 3900,
      "Entries": [
        ""
      ]
    },
    {
      "ID": 4000,
      "Entries": [
        ""
      ]
    },
    {
      "ID": 4100,
      "Entries": [
        ""
      ]
    },
    {
      "ID": 4200,
      "Entries": [
        ""
      ]
    },
    {
      "ID": 4300,
      "Entries": [
        ""
      ]
    },
    {
      "ID": 4400,
      "Entries": [
        ""
      ]
    },
    {
      "ID": 4500,
      "Entries": [
        ""
      ]
    },
    {
      "ID": 4600,
      "Entries": [
        ""
      ]
    },
    {
      "ID": 4700,
      "Entries": [
        ""
      ]
    },
    {
      "ID": 4800,
      "Entries": [
        ""
      ]
    },
    {
      "ID": 4900,
      "Entries": [
        ""
      ]
    },
    {
      "ID": 5000,
      "Entries": [
        ""
      ]
    },
    {
      "ID": 10000,
      "Entries": [
        ""
      ]
    },
    {
      "ID": 10100,
      "Entries": [
        ""
      ]
    },
    {
      "ID": 10200,
      "Entries": [
        ""
      ]
    },
    {
      "ID": 10300,
      "Entries": [
        ""
      ]
    },
    {
      "ID": 40000,
      "Entries": [
        ""
      ]
    },
    {
      "ID": 40100,
      "Entries": [
        ""
      ]
    },
    {
      "ID": 40200,
      "Entries": [
        ""
      ]
    },
    {
      "ID": 40300,
      "Entries": [
        ""
      ]
    },
    {
      "ID": 50000,
      "Entries": [
        ""
      ]
    },
    {
      "ID": 50100,
      "Entries": [
        ""
      ]
    },
    {
      "ID": 50200,
      "Entries": [
        ""
      ]
    },
    {
      "ID": 50300,
      "Entries": [
        ""
      ]
    },
    {
      "ID": 60000,
      "Entries": [
        ""
      ]
    },
    {
      "ID": 60100,
      "Entries": [
        ""
      ]
    },
    {
      "ID": 60200,
      "Entries": [
        ""
      ]
    },
    {
      "ID": 60300,
      "Entries": [
        ""
      ]
    },
    {
      "ID": 61000,
      "Entries": [
        ""
      ]
    },
    {
      "ID": 61100,
      "Entries": [
        ""
      ]
    },
    {
      "ID": 80000,
      "Entries": [
        ""
      ]
    },
    {
      "ID": 80100,
      "Entries": [
        ""
      ]
    },
    {
      "ID": 80200,
      "Entries": [
        ""
      ]
    },
    {
      "ID": 80300,
      "Entries": [
        ""
      ]
    },
    {
      "ID": 81100,
      "Entries": [
        ""
      ]
    },
    {
      "ID": 90000,
      "Entries": [
        ""
      ]
    },
    {
      "ID": 90100,
      "Entries": [
        ""
      ]
    },
    {
      "ID": 90200,
      "Entries": [
        ""
      ]
    },
    {
      "ID": 90300,
      "Entries": [
        ""
      ]
    },
    {
      "ID": 91100,
      "Entries": [
        ""
      ]
    },
    {
      "ID": 100000,
      "Entries": [
        ""
      ]
    },
    {
      "ID": 100100,
      "Entries": [
        ""
      ]
    },
    {
      "ID": 100200,
      "Entries": [
        ""
      ]
    },
    {
      "ID": 100300,
      "Entries": [
        ""
      ]
    },
    {
      "ID": 101100,
      "Entries": [
        ""
      ]
    },
    {
      "ID": 120000,
      "Entries": [
        ""
      ]
    },
    {
      "ID": 120100,
      "Entries": [
        ""
      ]
    },
    {
      "ID": 120200,
      "Entries": [
        ""
      ]
    },
    {
      "ID": 120300,
      "Entries": [
        ""
      ]
    },
    {
      "ID": 121000,
      "Entries": [
        ""
      ]
    },
    {
      "ID": 121100,
      "Entries": [
        ""
      ]
    },
    {
      "ID": 130000,
      "Entries": [
        ""
      ]
    },
    {
      "ID": 130100,
      "Entries": [
        ""
      ]
    },
    {
      "ID": 130200,
      "Entries": [
        ""
      ]
    },
    {
      "ID": 130300,
      "Entries": [
        ""
      ]
    },
    {
      "ID": 131100,
      "Entries": [
        ""
      ]
    },
    {
      "ID": 140000,
      "Entries": [
        ""
      ]
    },
    {
      "ID": 140100,
      "Entries": [
        ""
      ]
    },
    {
      "ID": 140200,
      "Entries": [
        ""
      ]
    },
    {
      "ID": 140300,
      "Entries": [
        ""
      ]
    },
    {
      "ID": 150000,
      "Entries": [
        ""
      ]
    },
    {
      "ID": 150100,
      "Entries": [
        ""
      ]
    },
    {
      "ID": 150200,
      "Entries": [
        ""
      ]
    },
    {
      "ID": 150300,
      "Entries": [
        ""
      ]
    },
    {
      "ID": 151100,
      "Entries": [
        ""
      ]
    },
    {
      "ID": 160000,
      "Entries": [
        ""
      ]
    },
    {
      "ID": 160100,
      "Entries": [
        ""
      ]
    },
    {
      "ID": 160300,
      "Entries": [
        ""
      ]
    },
    {
      "ID": 170000,
      "Entries": [
        ""
      ]
    },
    {
      "ID": 170100,
      "Entries": [
        ""
      ]
    },
    {
      "ID": 170200,
      "Entries": [
        ""
      ]
    },
    {
      "ID": 170300,
      "Entries": [
        ""
      ]
    },
    {
      "ID": 171100,
      "Entries": [
        ""
      ]
    },
    {
      "ID": 180000,
      "Entries": [
        ""
      ]
    },
    {
      "ID": 180100,
      "Entries": [
        ""
      ]
    },
    {
      "ID": 180200,
      "Entries": [
        ""
      ]
    },
    {
      "ID": 180300,
      "Entries": [
        ""
      ]
    },
    {
      "ID": 181100,
      "Entries": [
        ""
      ]
    },
    {
      "ID": 190000,
      "Entries": [
        ""
      ]
    },
    {
      "ID": 190100,
      "Entries": [
        ""
      ]
    },
    {
      "ID": 190200,
      "Entries": [
        ""
      ]
    },
    {
      "ID": 190300,
      "Entries": [
        ""
      ]
    },
    {
      "ID": 200000,
      "Entries": [
        ""
      ]
    },
    {
      "ID": 200100,
      "Entries": [
        ""
      ]
    },
    {
      "ID": 200200,
      "Entries": [
        ""
      ]
    },
    {
      "ID": 200300,
      "Entries": [
        ""
      ]
    },
    {
      "ID": 201000,
      "Entries": [
        ""
      ]
    },
    {
      "ID": 201100,
      "Entries": [
        ""
      ]
    },
    {
      "ID": 202100,
      "Entries": [
        ""
      ]
    },
    {
      "ID": 210000,
      "Entries": [
        ""
      ]
    },
    {
      "ID": 210100,
      "Entries": [
        ""
      ]
    },
    {
      "ID": 210200,
      "Entries": [
        ""
      ]
    },
    {
      "ID": 210300,
      "Entries": [
        ""
      ]
    },
    {
      "ID": 211100,
      "Entries": [
        ""
      ]
    },
    {
      "ID": 220000,
      "Entries": [
        ""
      ]
    },
    {
      "ID": 220100,
      "Entries": [
        ""
      ]
    },
    {
      "ID": 220300,
      "Entries": [
        ""
      ]
    },
    {
      "ID": 221100,
      "Entries": [
        ""
      ]
    },
    {
      "ID": 230000,
      "Entries": [
        ""
      ]
    },
    {
      "ID": 230100,
      "Entries": [
        ""
      ]
    },
    {
      "ID": 230200,
      "Entries": [
        ""
      ]
    },
    {
      "ID": 230300,
      "Entries": [
        ""
      ]
    },
    {
      "ID": 231000,
      "Entries": [
        ""
      ]
    },
    {
      "ID": 231100,
      "Entries": [
        ""
      ]
    },
    {
      "ID": 240000,
      "Entries": [
        ""
      ]
    },
    {
      "ID": 240100,
      "Entries": [
        ""
      ]
    },
    {
      "ID": 240200,
      "Entries": [
        ""
      ]
    },
    {
      "ID": 240300,
      "Entries": [
        ""
      ]
    },
    {
      "ID": 241100,
      "Entries": [
        ""
      ]
    },
    {
      "ID": 250000,
      "Entries": [
        ""
      ]
    },
    {
      "ID": 250100,
      "Entries": [
        ""
      ]
    },
    {
      "ID": 250300,
      "Entries": [
        ""
      ]
    },
    {
      "ID": 251100,
      "Entries": [
        ""
      ]
    },
    {
      "ID": 260000,
      "Entries": [
        ""
      ]
    },
    {
      "ID": 260100,
      "Entries": [
        ""
      ]
    },
    {
      "ID": 260200,
      "Entries": [
        ""
      ]
    },
    {
      "ID": 260300,
      "Entries": [
        ""
      ]
    },
    {
      "ID": 270000,
      "Entries": [
        ""
      ]
    },
    {
      "ID": 270100,
      "Entries": [
        ""
      ]
    },
    {
      "ID": 270200,
      "Entries": [
        ""
      ]
    },
    {
      "ID": 270300,
      "Entries": [
        ""
      ]
    },
    {
      "ID": 271100,
      "Entries": [
        ""
      ]
    },
    {
      "ID": 280000,
      "Entries": [
        ""
      ]
    },
    {
      "ID": 280100,
      "Entries": [
        ""
      ]
    },
    {
      "ID": 280200,
      "Entries": [
        ""
      ]
    },
    {
      "ID": 280300,
      "Entries": [
        ""
      ]
    },
    {
      "ID": 281100,
      "Entries": [
        ""
      ]
    },
    {
      "ID": 290000,
      "Entries": [
        ""
      ]
    },
    {
      "ID": 290100,
      "Entries": [
        ""
      ]
    },
    {
      "ID": 290200,
      "Entries": [
        ""
      ]
    },
    {
      "ID": 290300,
      "Entries": [
        ""
      ]
    },
    {
      "ID": 291000,
      "Entries": [
        ""
      ]
    },
    {
      "ID": 291100,
      "Entries": [
        ""
      ]
    },
    {
      "ID": 292000,
      "Entries": [
        ""
      ]
    },
    {
      "ID": 292100,
      "Entries": [
        ""
      ]
    },
    {
      "ID": 293000,
      "Entries": [
        ""
      ]
    },
    {
      "ID": 293100,
      "Entries": [
        ""
      ]
    },
    {
      "ID": 294000,
      "Entries": [
        ""
      ]
    },
    {
      "ID": 294100,
      "Entries": [
        ""
      ]
    },
    {
      "ID": 300000,
      "Entries": [
        ""
      ]
    },
    {
      "ID": 300100,
      "Entries": [
        ""
      ]
    },
    {
      "ID": 300300,
      "Entries": [
        ""
      ]
    },
    {
      "ID": 301000,
      "Entries": [
        ""
      ]
    },
    {
      "ID": 301100,
      "Entries": [
        ""
      ]
    },
    {
      "ID": 301300,
      "Entries": [
        ""
      ]
    },
    {
      "ID": 310000,
      "Entries": [
        ""
      ]
    },
    {
      "ID": 310100,
      "Entries": [
        ""
      ]
    },
    {
      "ID": 310300,
      "Entries": [
        ""
      ]
    },
    {
      "ID": 311100,
      "Entries": [
        ""
      ]
    },
    {
      "ID": 320000,
      "Entries": [
        ""
      ]
    },
    {
      "ID": 320100,
      "Entries": [
        ""
      ]
    },
    {
      "ID": 320300,
      "Entries": [
        ""
      ]
    },
    {
      "ID": 330000,
      "Entries": [
        ""
      ]
    },
    {
      "ID": 330100,
      "Entries": [
        ""
      ]
    },
    {
      "ID": 330200,
      "Entries": [
        ""
      ]
    },
    {
      "ID": 330300,
      "Entries": [
        ""
      ]
    },
    {
      "ID": 331100,
      "Entries": [
        ""
      ]
    },
    {
      "ID": 340000,
      "Entries": [
        ""
      ]
    },
    {
      "ID": 340100,
      "Entries": [
        ""
      ]
    },
    {
      "ID": 340200,
      "Entries": [
        ""
      ]
    },
    {
      "ID": 340300,
      "Entries": [
        ""
      ]
    },
    {
      "ID": 341000,
      "Entries": [
        ""
      ]
    },
    {
      "ID": 341100,
      "Entries": [
        ""
      ]
    },
    {
      "ID": 350000,
      "Entries": [
        ""
      ]
    },
    {
      "ID": 350100,
      "Entries": [
        ""
      ]
    },
    {
      "ID": 350200,
      "Entries": [
        ""
      ]
    },
    {
      "ID": 350300,
      "Entries": [
        ""
      ]
    },
    {
      "ID": 351000,
      "Entries": [
        ""
      ]
    },
    {
      "ID": 351100,
      "Entries": [
        ""
      ]
    },
    {
      "ID": 351200,
      "Entries": [
        ""
      ]
    },
    {
      "ID": 351300,
      "Entries": [
        ""
      ]
    },
    {
      "ID": 360000,
      "Entries": [
        ""
      ]
    },
    {
      "ID": 360100,
      "Entries": [
        ""
      ]
    },
    {
      "ID": 360200,
      "Entries": [
        ""
      ]
    },
    {
      "ID": 360300,
      "Entries": [
        ""
      ]
    },
    {
      "ID": 361100,
      "Entries": [
        ""
      ]
    },
    {
      "ID": 370000,
      "Entries": [
        ""
      ]
    },
    {
      "ID": 370100,
      "Entries": [
        ""
      ]
    },
    {
      "ID": 370300,
      "Entries": [
        ""
      ]
    },
    {
      "ID": 371100,
      "Entries": [
        ""
      ]
    },
    {
      "ID": 380000,
      "Entries": [
        ""
      ]
    },
    {
      "ID": 380100,
      "Entries": [
        ""
      ]
    },
    {
      "ID": 390000,
      "Entries": [
        ""
      ]
    },
    {
      "ID": 390100,
      "Entries": [
        ""
      ]
    },
    {
      "ID": 390300,
      "Entries": [
        ""
      ]
    },
    {
      "ID": 420000,
      "Entries": [
        ""
      ]
    },
    {
      "ID": 420100,
      "Entries": [
        ""
      ]
    },
    {
      "ID": 420200,
      "Entries": [
        ""
      ]
    },
    {
      "ID": 420300,
      "Entries": [
        ""
      ]
    },
    {
      "ID": 430000,
      "Entries": [
        ""
      ]
    },
    {
      "ID": 430100,
      "Entries": [
        ""
      ]
    },
    {
      "ID": 430300,
      "Entries": [
        ""
      ]
    },
    {
      "ID": 440000,
      "Entries": [
        ""
      ]
    },
    {
      "ID": 460000,
      "Entries": [
        ""
      ]
    },
    {
      "ID": 460100,
      "Entries": [
        ""
      ]
    },
    {
      "ID": 460200,
      "Entries": [
        ""
      ]
    },
    {
      "ID": 460300,
      "Entries": [
        ""
      ]
    },
    {
      "ID": 461100,
      "Entries": [
        ""
      ]
    },
    {
      "ID": 470000,
      "Entries": [
        ""
      ]
    },
    {
      "ID": 470100,
      "Entries": [
        ""
      ]
    },
    {
      "ID": 470200,
      "Entries": [
        ""
      ]
    },
    {
      "ID": 470300,
      "Entries": [
        ""
      ]
    },
    {
      "ID": 471100,
      "Entries": [
        ""
      ]
    },
    {
      "ID": 480100,
      "Entries": [
        ""
      ]
    },
    {
      "ID": 481100,
      "Entries": [
        ""
      ]
    },
    {
      "ID": 510000,
      "Entries": [
        ""
      ]
    },
    {
      "ID": 510100,
      "Entries": [
        ""
      ]
    },
    {
      "ID": 510200,
      "Entries": [
        ""
      ]
    },
    {
      "ID": 510300,
      "Entries": [
        ""
      ]
    },
    {
      "ID": 520000,
      "Entries": [
        ""
      ]
    },
    {
      "ID": 520100,
      "Entries": [
        ""
      ]
    },
    {
      "ID": 520200,
      "Entries": [
        ""
      ]
    },
    {
      "ID": 520300,
      "Entries": [
        ""
      ]
    },
    {
      "ID": 530000,
      "Entries": [
        ""
      ]
    },
    {
      "ID": 530100,
      "Entries": [
        ""
      ]
    },
    {
      "ID": 530200,
      "Entries": [
        ""
      ]
    },
    {
      "ID": 530300,
      "Entries": [
        ""
      ]
    },
    {
      "ID": 540000,
      "Entries": [
        ""
      ]
    },
    {
      "ID": 540100,
      "Entries": [
        ""
      ]
    },
    {
      "ID": 540200,
      "Entries": [
        ""
      ]
    },
    {
      "ID": 540300,
      "Entries": [
        ""
      ]
    },
    {
      "ID": 541100,
      "Entries": [
        ""
      ]
    },
    {
      "ID": 570000,
      "Entries": [
        ""
      ]
    },
    {
      "ID": 570100,
      "Entries": [
        ""
      ]
    },
    {
      "ID": 570200,
      "Entries": [
        ""
      ]
    },
    {
      "ID": 570300,
      "Entries": [
        ""
      ]
    },
    {
      "ID": 571000,
      "Entries": [
        ""
      ]
    },
    {
      "ID": 571100,
      "Entries": [
        ""
      ]
    },
    {
      "ID": 572100,
      "Entries": [
        ""
      ]
    },
    {
      "ID": 573100,
      "Entries": [
        ""
      ]
    },
    {
      "ID": 580000,
      "Entries": [
        ""
      ]
    },
    {
      "ID": 580100,
      "Entries": [
        ""
      ]
    },
    {
      "ID": 580200,
      "Entries": [
        ""
      ]
    },
    {
      "ID": 580300,
      "Entries": [
        ""
      ]
    },
    {
      "ID": 581000,
      "Entries": [
        ""
      ]
    },
    {
      "ID": 581100,
      "Entries": [
        ""
      ]
    },
    {
      "ID": 581200,
      "Entries": [
        ""
      ]
    },
    {
      "ID": 590000,
      "Entries": [
        ""
      ]
    },
    {
      "ID": 590100,
      "Entries": [
        ""
      ]
    },
    {
      "ID": 590200,
      "Entries": [
        ""
      ]
    },
    {
      "ID": 590300,
      "Entries": [
        ""
      ]
    },
    {
      "ID": 591100,
      "Entries": [
        ""
      ]
    },
    {
      "ID": 600000,
      "Entries": [
        ""
      ]
    },
    {
      "ID": 600100,
      "Entries": [
        ""
      ]
    },
    {
      "ID": 600200,
      "Entries": [
        ""
      ]
    },
    {
      "ID": 600300,
      "Entries": [
        ""
      ]
    },
    {
      "ID": 601100,
      "Entries": [
        ""
      ]
    },
    {
      "ID": 610000,
      "Entries": [
        ""
      ]
    },
    {
      "ID": 610100,
      "Entries": [
        ""
      ]
    },
    {
      "ID": 610200,
      "Entries": [
        ""
      ]
    },
    {
      "ID": 610300,
      "Entries": [
        ""
      ]
    },
    {
      "ID": 611000,
      "Entries": [
        ""
      ]
    },
    {
      "ID": 611100,
      "Entries": [
        ""
      ]
    },
    {
      "ID": 620000,
      "Entries": [
        ""
      ]
    },
    {
      "ID": 620100,
      "Entries": [
        ""
      ]
    },
    {
      "ID": 620300,
      "Entries": [
        ""
      ]
    },
    {
      "ID": 621100,
      "Entries": [
        ""
      ]
    },
    {
      "ID": 622100,
      "Entries": [
        ""
      ]
    },
    {
      "ID": 630000,
      "Entries": [
        ""
      ]
    },
    {
      "ID": 630100,
      "Entries": [
        ""
      ]
    },
    {
      "ID": 630200,
      "Entries": [
        ""
      ]
    },
    {
      "ID": 630300,
      "Entries": [
        ""
      ]
    },
    {
      "ID": 631100,
      "Entries": [
        ""
      ]
    },
    {
      "ID": 640000,
      "Entries": [
        ""
      ]
    },
    {
      "ID": 640100,
      "Entries": [
        ""
      ]
    },
    {
      "ID": 640200,
      "Entries": [
        ""
      ]
    },
    {
      "ID": 640300,
      "Entries": [
        ""
      ]
    },
    {
      "ID": 641100,
      "Entries": [
        ""
      ]
    },
    {
      "ID": 650000,
      "Entries": [
        ""
      ]
    },
    {
      "ID": 650100,
      "Entries": [
        ""
      ]
    },
    {
      "ID": 650200,
      "Entries": [
        ""
      ]
    },
    {
      "ID": 650300,
      "Entries": [
        ""
      ]
    },
    {
      "ID": 651000,
      "Entries": [
        ""
      ]
    },
    {
      "ID": 652100,
      "Entries": [
        ""
      ]
    },
    {
      "ID": 660000,
      "Entries": [
        ""
      ]
    },
    {
      "ID": 660100,
      "Entries": [
        ""
      ]
    },
    {
      "ID": 660200,
      "Entries": [
        ""
      ]
    },
    {
      "ID": 660300,
      "Entries": [
        ""
      ]
    },
    {
      "ID": 661100,
      "Entries": [
        ""
      ]
    },
    {
      "ID": 670000,
      "Entries": [
        ""
      ]
    },
    {
      "ID": 670100,
      "Entries": [
        ""
      ]
    },
    {
      "ID": 670200,
      "Entries": [
        ""
      ]
    },
    {
      "ID": 670300,
      "Entries": [
        ""
      ]
    },
    {
      "ID": 680000,
      "Entries": [
        ""
      ]
    },
    {
      "ID": 680100,
      "Entries": [
        ""
      ]
    },
    {
      "ID": 680200,
      "Entries": [
        ""
      ]
    },
    {
      "ID": 680300,
      "Entries": [
        ""
      ]
    },
    {
      "ID": 681100,
      "Entries": [
        ""
      ]
    },
    {
      "ID": 690000,
      "Entries": [
        ""
      ]
    },
    {
      "ID": 690100,
      "Entries": [
        ""
      ]
    },
    {
      "ID": 690200,
      "Entries": [
        ""
      ]
    },
    {
      "ID": 690300,
      "Entries": [
        ""
      ]
    },
    {
      "ID": 700000,
      "Entries": [
        ""
      ]
    },
    {
      "ID": 700100,
      "Entries": [
        ""
      ]
    },
    {
      "ID": 700200,
      "Entries": [
        ""
      ]
    },
    {
      "ID": 700300,
      "Entries": [
        ""
      ]
    },
    {
      "ID": 701000,
      "Entries": [
        ""
      ]
    },
    {
      "ID": 702000,
      "Entries": [
        ""
      ]
    },
    {
      "ID": 720000,
      "Entries": [
        ""
      ]
    },
    {
      "ID": 720100,
      "Entries": [
        ""
      ]
    },
    {
      "ID": 720200,
      "Entries": [
        ""
      ]
    },
    {
      "ID": 720300,
      "Entries": [
        ""
      ]
    },
    {
      "ID": 721100,
      "Entries": [
        ""
      ]
    },
    {
      "ID": 730000,
      "Entries": [
        ""
      ]
    },
    {
      "ID": 730100,
      "Entries": [
        ""
      ]
    },
    {
      "ID": 730200,
      "Entries": [
        ""
      ]
    },
    {
      "ID": 730300,
      "Entries": [
        ""
      ]
    },
    {
      "ID": 740000,
      "Entries": [
        ""
      ]
    },
    {
      "ID": 740100,
      "Entries": [
        ""
      ]
    },
    {
      "ID": 740200,
      "Entries": [
        ""
      ]
    },
    {
      "ID": 740300,
      "Entries": [
        ""
      ]
    },
    {
      "ID": 741000,
      "Entries": [
        ""
      ]
    },
    {
      "ID": 742000,
      "Entries": [
        ""
      ]
    },
    {
      "ID": 760000,
      "Entries": [
        ""
      ]
    },
    {
      "ID": 760100,
      "Entries": [
        ""
      ]
    },
    {
      "ID": 760200,
      "Entries": [
        ""
      ]
    },
    {
      "ID": 760300,
      "Entries": [
        ""
      ]
    },
    {
      "ID": 761100,
      "Entries": [
        ""
      ]
    },
    {
      "ID": 770000,
      "Entries": [
        ""
      ]
    },
    {
      "ID": 770100,
      "Entries": [
        ""
      ]
    },
    {
      "ID": 770200,
      "Entries": [
        ""
      ]
    },
    {
      "ID": 770300,
      "Entries": [
        ""
      ]
    },
    {
      "ID": 771100,
      "Entries": [
        ""
      ]
    },
    {
      "ID": 780000,
      "Entries": [
        ""
      ]
    },
    {
      "ID": 780100,
      "Entries": [
        ""
      ]
    },
    {
      "ID": 780200,
      "Entries": [
        ""
      ]
    },
    {
      "ID": 780300,
      "Entries": [
        ""
      ]
    },
    {
      "ID": 781100,
      "Entries": [
        ""
      ]
    },
    {
      "ID": 790000,
      "Entries": [
        ""
      ]
    },
    {
      "ID": 790100,
      "Entries": [
        ""
      ]
    },
    {
      "ID": 790200,
      "Entries": [
        ""
      ]
    },
    {
      "ID": 790300,
      "Entries": [
        ""
      ]
    },
    {
      "ID": 791100,
      "Entries": [
        ""
      ]
    },
    {
      "ID": 800000,
      "Entries": [
        ""
      ]
    },
    {
      "ID": 800100,
      "Entries": [
        ""
      ]
    },
    {
      "ID": 801000,
      "Entries": [
        ""
      ]
    },
    {
      "ID": 801100,
      "Entries": [
        ""
      ]
    },
    {
      "ID": 802000,
      "Entries": [
        ""
      ]
    },
    {
      "ID": 802100,
      "Entries": [
        ""
      ]
    },
    {
      "ID": 810000,
      "Entries": [
        ""
      ]
    },
    {
      "ID": 810100,
      "Entries": [
        ""
      ]
    },
    {
      "ID": 810300,
      "Entries": [
        ""
      ]
    },
    {
      "ID": 811000,
      "Entries": [
        ""
      ]
    },
    {
      "ID": 811100,
      "Entries": [
        ""
      ]
    },
    {
      "ID": 812000,
      "Entries": [
        ""
      ]
    },
    {
      "ID": 812100,
      "Entries": [
        ""
      ]
    },
    {
      "ID": 820000,
      "Entries": [
        ""
      ]
    },
    {
      "ID": 830000,
      "Entries": [
        ""
      ]
    },
    {
      "ID": 830100,
      "Entries": [
        ""
      ]
    },
    {
      "ID": 830200,
      "Entries": [
        ""
      ]
    },
    {
      "ID": 830300,
      "Entries": [
        ""
      ]
    },
    {
      "ID": 831000,
      "Entries": [
        ""
      ]
    },
    {
      "ID": 832000,
      "Entries": [
        ""
      ]
    },
    {
      "ID": 833000,
      "Entries": [
        ""
      ]
    },
    {
      "ID": 834000,
      "Entries": [
        ""
      ]
    },
    {
      "ID": 834100,
      "Entries": [
        ""
      ]
    },
    {
      "ID": 835000,
      "Entries": [
        ""
      ]
    },
    {
      "ID": 835100,
      "Entries": [
        ""
      ]
    },
    {
      "ID": 835200,
      "Entries": [
        ""
      ]
    },
    {
      "ID": 835300,
      "Entries": [
        ""
      ]
    },
    {
      "ID": 836000,
      "Entries": [
        ""
      ]
    },
    {
      "ID": 840000,
      "Entries": [
        ""
      ]
    },
    {
      "ID": 840100,
      "Entries": [
        ""
      ]
    },
    {
      "ID": 850000,
      "Entries": [
        ""
      ]
    },
    {
      "ID": 860000,
      "Entries": [
        ""
      ]
    },
    {
      "ID": 860100,
      "Entries": [
        ""
      ]
    },
    {
      "ID": 860200,
      "Entries": [
        ""
      ]
    },
    {
      "ID": 860300,
      "Entries": [
        ""
      ]
    },
    {
      "ID": 861100,
      "Entries": [
        ""
      ]
    },
    {
      "ID": 870000,
      "Entries": [
        ""
      ]
    },
    {
      "ID": 870100,
      "Entries": [
        ""
      ]
    },
    {
      "ID": 870200,
      "Entries": [
        ""
      ]
    },
    {
      "ID": 870300,
      "Entries": [
        ""
      ]
    },
    {
      "ID": 871100,
      "Entries": [
        ""
      ]
    },
    {
      "ID": 872000,
      "Entries": [
        ""
      ]
    },
    {
      "ID": 872100,
      "Entries": [
        ""
      ]
    },
    {
      "ID": 872200,
      "Entries": [
        ""
      ]
    },
    {
      "ID": 872300,
      "Entries": [
        ""
      ]
    },
    {
      "ID": 873000,
      "Entries": [
        ""
      ]
    },
    {
      "ID": 880000,
      "Entries": [
        ""
      ]
    },
    {
      "ID": 880100,
      "Entries": [
        ""
      ]
    },
    {
      "ID": 880200,
      "Entries": [
        ""
      ]
    },
    {
      "ID": 880300,
      "Entries": [
        ""
      ]
    },
    {
      "ID": 881000,
      "Entries": [
        ""
      ]
    },
    {
      "ID": 881100,
      "Entries": [
        ""
      ]
    },
    {
      "ID": 890000,
      "Entries": [
        ""
      ]
    },
    {
      "ID": 890100,
      "Entries": [
        ""
      ]
    },
    {
      "ID": 890300,
      "Entries": [
        ""
      ]
    },
    {
      "ID": 891000,
      "Entries": [
        ""
      ]
    },
    {
      "ID": 892100,
      "Entries": [
        ""
      ]
    },
    {
      "ID": 900000,
      "Entries": [
        ""
      ]
    },
    {
      "ID": 900100,
      "Entries": [
        ""
      ]
    },
    {
      "ID": 900200,
      "Entries": [
        ""
      ]
    },
    {
      "ID": 900300,
      "Entries": [
        ""
      ]
    },
    {
      "ID": 901100,
      "Entries": [
        ""
      ]
    },
    {
      "ID": 901200,
      "Entries": [
        ""
      ]
    },
    {
      "ID": 901600,
      "Entries": [
        ""
      ]
    },
    {
      "ID": 902000,
      "Entries": [
        ""
      ]
    },
    {
      "ID": 902100,
      "Entries": [
        ""
      ]
    },
    {
      "ID": 902300,
      "Entries": [
        ""
      ]
    },
    {
      "ID": 903100,
      "Entries": [
        ""
      ]
    },
    {
      "ID": 904100,
      "Entries": [
        ""
      ]
    },
    {
      "ID": 910000,
      "Entries": [
        ""
      ]
    },
    {
      "ID": 910100,
      "Entries": [
        ""
      ]
    },
    {
      "ID": 910200,
      "Entries": [
        ""
      ]
    },
    {
      "ID": 910300,
      "Entries": [
        ""
      ]
    },
    {
      "ID": 911000,
      "Entries": [
        ""
      ]
    },
    {
      "ID": 911100,
      "Entries": [
        ""
      ]
    },
    {
      "ID": 912000,
      "Entries": [
        ""
      ]
    },
    {
      "ID": 912100,
      "Entries": [
        ""
      ]
    },
    {
      "ID": 912200,
      "Entries": [
        ""
      ]
    },
    {
      "ID": 912300,
      "Entries": [
        ""
      ]
    },
    {
      "ID": 913000,
      "Entries": [
        ""
      ]
    },
    {
      "ID": 920000,
      "Entries": [
        ""
      ]
    },
    {
      "ID": 930000,
      "Entries": [
        ""
      ]
    },
    {
      "ID": 930100,
      "Entries": [
        ""
      ]
    },
    {
      "ID": 930200,
      "Entries": [
        ""
      ]
    },
    {
      "ID": 930300,
      "Entries": [
        ""
      ]
    },
    {
      "ID": 931100,
      "Entries": [
        ""
      ]
    },
    {
      "ID": 940000,
      "Entries": [
        ""
      ]
    },
    {
      "ID": 940100,
      "Entries": [
        ""
      ]
    },
    {
      "ID": 940200,
      "Entries": [
        ""
      ]
    },
    {
      "ID": 940300,
      "Entries": [
        ""
      ]
    },
    {
      "ID": 941000,
      "Entries": [
        ""
      ]
    },
    {
      "ID": 950000,
      "Entries": [
        ""
      ]
    },
    {
      "ID": 950100,
      "Entries": [
        ""
      ]
    },
    {
      "ID": 950200,
      "Entries": [
        ""
      ]
    },
    {
      "ID": 950300,
      "Entries": [
        ""
      ]
    },
    {
      "ID": 951100,
      "Entries": [
        ""
      ]
    },
    {
      "ID": 960000,
      "Entries": [
        ""
      ]
    },
    {
      "ID": 960100,
      "Entries": [
        ""
      ]
    },
    {
      "ID": 960300,
      "Entries": [
        ""
      ]
    },
    {
      "ID": 961000,
      "Entries": [
        ""
      ]
    },
    {
      "ID": 961100,
      "Entries": [
        ""
      ]
    },
    {
      "ID": 962100,
      "Entries": [
        ""
      ]
    },
    {
      "ID": 963000,
      "Entries": [
        ""
      ]
    },
    {
      "ID": 963100,
      "Entries": [
        ""
      ]
    },
    {
      "ID": 963200,
      "Entries": [
        ""
      ]
    },
    {
      "ID": 964000,
      "Entries": [
        ""
      ]
    },
    {
      "ID": 964100,
      "Entries": [
        ""
      ]
    },
    {
      "ID": 965000,
      "Entries": [
        ""
      ]
    },
    {
      "ID": 965100,
      "Entries": [
        ""
      ]
    },
    {
      "ID": 965300,
      "Entries": [
        ""
      ]
    },
    {
      "ID": 966000,
      "Entries": [
        ""
      ]
    },
    {
      "ID": 967000,
      "Entries": [
        ""
      ]
    },
    {
      "ID": 970000,
      "Entries": [
        ""
      ]
    },
    {
      "ID": 970100,
      "Entries": [
        ""
      ]
    },
    {
      "ID": 970200,
      "Entries": [
        ""
      ]
    },
    {
      "ID": 970300,
      "Entries": [
        ""
      ]
    },
    {
      "ID": 980000,
      "Entries": [
        ""
      ]
    },
    {
      "ID": 980100,
      "Entries": [
        ""
      ]
    },
    {
      "ID": 980200,
      "Entries": [
        ""
      ]
    },
    {
      "ID": 980300,
      "Entries": [
        ""
      ]
    },
    {
      "ID": 981100,
      "Entries": [
        ""
      ]
    },
    {
      "ID": 990000,
      "Entries": [
        ""
      ]
    },
    {
      "ID": 990100,
      "Entries": [
        ""
      ]
    },
    {
      "ID": 990200,
      "Entries": [
        ""
      ]
    },
    {
      "ID": 990300,
      "Entries": [
        ""
      ]
    },
    {
      "ID": 991100,
      "Entries": [
        ""
      ]
    },
    {
      "ID": 992000,
      "Entries": [
        ""
      ]
    },
    {
      "ID": 1000000,
      "Entries": [
        ""
      ]
    },
    {
      "ID": 1000100,
      "Entries": [
        ""
      ]
    },
    {
      "ID": 1000200,
      "Entries": [
        ""
      ]
    },
    {
      "ID": 1000300,
      "Entries": [
        ""
      ]
    },
    {
      "ID": 1010000,
      "Entries": [
        ""
      ]
    },
    {
      "ID": 1010100,
      "Entries": [
        ""
      ]
    },
    {
      "ID": 1010300,
      "Entries": [
        ""
      ]
    },
    {
      "ID": 1011100,
      "Entries": [
        ""
      ]
    },
    {
      "ID": 1020100,
      "Entries": [
        ""
      ]
    },
    {
      "ID": 1020200,
      "Entries": [
        ""
      ]
    },
    {
      "ID": 1020300,
      "Entries": [
        ""
      ]
    },
    {
      "ID": 1030000,
      "Entries": [
        ""
      ]
    },
    {
      "ID": 1030100,
      "Entries": [
        ""
      ]
    },
    {
      "ID": 1040000,
      "Entries": [
        ""
      ]
    },
    {
      "ID": 1040100,
      "Entries": [
        ""
      ]
    },
    {
      "ID": 1040200,
      "Entries": [
        ""
      ]
    },
    {
      "ID": 1040300,
      "Entries": [
        ""
      ]
    },
    {
      "ID": 1050100,
      "Entries": [
        ""
      ]
    },
    {
      "ID": 1060000,
      "Entries": [
        ""
      ]
    },
    {
      "ID": 1060100,
      "Entries": [
        ""
      ]
    },
    {
      "ID": 1070000,
      "Entries": [
        ""
      ]
    },
    {
      "ID": 1070100,
      "Entries": [
        ""
      ]
    },
    {
      "ID": 1070200,
      "Entries": [
        ""
      ]
    },
    {
      "ID": 1070300,
      "Entries": [
        ""
      ]
    },
    {
      "ID": 1080000,
      "Entries": [
        ""
      ]
    },
    {
      "ID": 1081000,
      "Entries": [
        ""
      ]
    },
    {
      "ID": 1082000,
      "Entries": [
        ""
      ]
    },
    {
      "ID": 1083000,
      "Entries": [
        ""
      ]
    },
    {
      "ID": 1084000,
      "Entries": [
        ""
      ]
    },
    {
      "ID": 1085000,
      "Entries": [
        ""
      ]
    },
    {
      "ID": 1090000,
      "Entries": [
        ""
      ]
    },
    {
      "ID": 1100000,
      "Entries": [
        ""
      ]
    },
    {
      "ID": 1100100,
      "Entries": [
        ""
      ]
    },
    {
      "ID": 1100200,
      "Entries": [
        ""
      ]
    },
    {
      "ID": 1100300,
      "Entries": [
        ""
      ]
    },
    {
      "ID": 1101000,
      "Entries": [
        ""
      ]
    },
    {
      "ID": 1101100,
      "Entries": [
        ""
      ]
    },
    {
      "ID": 1102100,
      "Entries": [
        ""
      ]
    },
    {
      "ID": 1110000,
      "Entries": [
        ""
      ]
    },
    {
      "ID": 1120000,
      "Entries": [
        ""
      ]
    },
    {
      "ID": 1130000,
      "Entries": [
        ""
      ]
    },
    {
      "ID": 1130100,
      "Entries": [
        ""
      ]
    },
    {
      "ID": 1130200,
      "Entries": [
        ""
      ]
    },
    {
      "ID": 1130300,
      "Entries": [
        ""
      ]
    },
    {
      "ID": 1300000,
      "Entries": [
        ""
      ]
    },
    {
      "ID": 1301000,
      "Entries": [
        ""
      ]
    },
    {
      "ID": 1400000,
      "Entries": [
        ""
      ]
    },
    {
      "ID": 1400100,
      "Entries": [
        ""
      ]
    },
    {
      "ID": 1400200,
      "Entries": [
        ""
      ]
    },
    {
      "ID": 1400300,
      "Entries": [
        ""
      ]
    },
    {
      "ID": 1401000,
      "Entries": [
        ""
      ]
    },
    {
      "ID": 1500000,
      "Entries": [
        ""
      ]
    },
    {
      "ID": 1500100,
      "Entries": [
        ""
      ]
    },
    {
      "ID": 1500200,
      "Entries": [
        ""
      ]
    },
    {
      "ID": 1500300,
      "Entries": [
        ""
      ]
    },
    {
      "ID": 1600000,
      "Entries": [
        ""
      ]
    },
    {
      "ID": 1610000,
      "Entries": [
        ""
      ]
    },
    {
      "ID": 1700000,
      "Entries": [
        ""
      ]
    },
    {
      "ID": 1700100,
      "Entries": [
        ""
      ]
    },
    {
      "ID": 1700200,
      "Entries": [
        ""
      ]
    },
    {
      "ID": 1700300,
      "Entries": [
        ""
      ]
    },
    {
      "ID": 1710000,
      "Entries": [
        ""
      ]
    },
    {
      "ID": 1710100,
      "Entries": [
        ""
      ]
    },
    {
      "ID": 1710200,
      "Entries": [
        ""
      ]
    },
    {
      "ID": 1710300,
      "Entries": [
        ""
      ]
    },
    {
      "ID": 1720000,
      "Entries": [
        ""
      ]
    },
    {
      "ID": 1720100,
      "Entries": [
        ""
      ]
    },
    {
      "ID": 1720200,
      "Entries": [
        ""
      ]
    },
    {
      "ID": 1720300,
      "Entries": [
        ""
      ]
    },
    {
      "ID": 1730000,
      "Entries": [
        ""
      ]
    },
    {
      "ID": 1730100,
      "Entries": [
        ""
      ]
    },
    {
      "ID": 1730200,
      "Entries": [
        ""
      ]
    },
    {
      "ID": 1730300,
      "Entries": [
        ""
      ]
    },
    {
      "ID": 1740100,
      "Entries": [
        ""
      ]
    },
    {
      "ID": 1740200,
      "Entries": [
        ""
      ]
    },
    {
      "ID": 1740300,
      "Entries": [
        ""
      ]
    },
    {
      "ID": 1750000,
      "Entries": [
        ""
      ]
    },
    {
      "ID": 1750100,
      "Entries": [
        ""
      ]
    },
    {
      "ID": 1750200,
      "Entries": [
        ""
      ]
    },
    {
      "ID": 1750300,
      "Entries": [
        ""
      ]
    },
    {
      "ID": 1760000,
      "Entries": [
        ""
      ]
    },
    {
      "ID": 1760100,
      "Entries": [
        ""
      ]
    },
    {
      "ID": 1760200,
      "Entries": [
        ""
      ]
    },
    {
      "ID": 1760300,
      "Entries": [
        ""
      ]
    },
    {
      "ID": 1761100,
      "Entries": [
        ""
      ]
    },
    {
      "ID": 1770000,
      "Entries": [
        ""
      ]
    },
    {
      "ID": 1770100,
      "Entries": [
        ""
      ]
    },
    {
      "ID": 1770200,
      "Entries": [
        ""
      ]
    },
    {
      "ID": 1770300,
      "Entries": [
        ""
      ]
    },
    {
      "ID": 1771100,
      "Entries": [
        ""
      ]
    },
    {
      "ID": 1780000,
      "Entries": [
        ""
      ]
    },
    {
      "ID": 1780100,
      "Entries": [
        ""
      ]
    },
    {
      "ID": 1780200,
      "Entries": [
        ""
      ]
    },
    {
      "ID": 1780300,
      "Entries": [
        ""
      ]
    },
    {
      "ID": 1781100,
      "Entries": [
        ""
      ]
    },
    {
      "ID": 1790000,
      "Entries": [
        ""
      ]
    },
    {
      "ID": 1790100,
      "Entries": [
        ""
      ]
    },
    {
      "ID": 1790200,
      "Entries": [
        ""
      ]
    },
    {
      "ID": 1790300,
      "Entries": [
        ""
      ]
    },
    {
      "ID": 1791100,
      "Entries": [
        ""
      ]
    },
    {
      "ID": 1800000,
      "Entries": [
        ""
      ]
    },
    {
      "ID": 1800100,
      "Entries": [
        ""
      ]
    },
    {
      "ID": 1800200,
      "Entries": [
        ""
      ]
    },
    {
      "ID": 1800300,
      "Entries": [
        ""
      ]
    },
    {
      "ID": 1801100,
      "Entries": [
        ""
      ]
    },
    {
      "ID": 1810100,
      "Entries": [
        ""
      ]
    },
    {
      "ID": 1810200,
      "Entries": [
        ""
      ]
    },
    {
      "ID": 1810300,
      "Entries": [
        ""
      ]
    },
    {
      "ID": 1811100,
      "Entries": [
        ""
      ]
    },
    {
      "ID": 1820000,
      "Entries": [
        ""
      ]
    },
    {
      "ID": 1820100,
      "Entries": [
        ""
      ]
    },
    {
      "ID": 1820200,
      "Entries": [
        ""
      ]
    },
    {
      "ID": 1820300,
      "Entries": [
        ""
      ]
    },
    {
      "ID": 1821100,
      "Entries": [
        ""
      ]
    },
    {
      "ID": 1830000,
      "Entries": [
        ""
      ]
    },
    {
      "ID": 1830100,
      "Entries": [
        ""
      ]
    },
    {
      "ID": 1830200,
      "Entries": [
        ""
      ]
    },
    {
      "ID": 1830300,
      "Entries": [
        ""
      ]
    },
    {
      "ID": 1840000,
      "Entries": [
        ""
      ]
    },
    {
      "ID": 1840100,
      "Entries": [
        ""
      ]
    },
    {
      "ID": 1850000,
      "Entries": [
        ""
      ]
    },
    {
      "ID": 1850100,
      "Entries": [
        ""
      ]
    },
    {
      "ID": 1860000,
      "Entries": [
        ""
      ]
    },
    {
      "ID": 1860100,
      "Entries": [
        ""
      ]
    },
    {
      "ID": 1870100,
      "Entries": [
        ""
      ]
    },
    {
      "ID": 1880000,
      "Entries": [
        ""
      ]
    },
    {
      "ID": 1880100,
      "Entries": [
        ""
      ]
    },
    {
      "ID": 1890000,
      "Entries": [
        ""
      ]
    },
    {
      "ID": 1890100,
      "Entries": [
        ""
      ]
    },
    {
      "ID": 1890200,
      "Entries": [
        ""
      ]
    },
    {
      "ID": 1890300,
      "Entries": [
        ""
      ]
    },
    {
      "ID": 1900000,
      "Entries": [
        ""
      ]
    },
    {
      "ID": 1901000,
      "Entries": [
        ""
      ]
    },
    {
      "ID": 1902000,
      "Entries": [
        ""
      ]
    },
    {
      "ID": 1910000,
      "Entries": [
        ""
      ]
    },
    {
      "ID": 1920000,
      "Entries": [
        ""
      ]
    },
    {
      "ID": 1930100,
      "Entries": [
        ""
      ]
    },
    {
      "ID": 1930300,
      "Entries": [
        ""
      ]
    },
    {
      "ID": 1932100,
      "Entries": [
        ""
      ]
    },
    {
      "ID": 1940000,
      "Entries": [
        ""
      ]
    },
    {
      "ID": 1940100,
      "Entries": [
        ""
      ]
    },
    {
      "ID": 1941100,
      "Entries": [
        ""
      ]
    },
    {
      "ID": 1950100,
      "Entries": [
        ""
      ]
    },
    {
      "ID": 1950200,
      "Entries": [
        ""
      ]
    },
    {
      "ID": 1950300,
      "Entries": [
        ""
      ]
    },
    {
      "ID": 1960100,
      "Entries": [
        ""
      ]
    },
    {
      "ID": 1960200,
      "Entries": [
        ""
      ]
    },
    {
      "ID": 1970100,
      "Entries": [
        ""
      ]
    },
    {
      "ID": 1970200,
      "Entries": [
        ""
      ]
    },
    {
      "ID": 1971100,
      "Entries": [
        ""
      ]
    },
    {
      "ID": 1971200,
      "Entries": [
        ""
      ]
    },
    {
      "ID": 1980000,
      "Entries": [
        ""
      ]
    },
    {
      "ID": 1980100,
      "Entries": [
        ""
      ]
    },
    {
      "ID": 1980200,
      "Entries": [
        ""
      ]
    },
    {
      "ID": 1990000,
      "Entries": [
        ""
      ]
    },
    {
      "ID": 1990100,
      "Entries": [
        ""
      ]
    },
    {
      "ID": 1991100,
      "Entries": [
        ""
      ]
    },
    {
      "ID": 2000000,
      "Entries": [
        ""
      ]
    },
    {
      "ID": 2000100,
      "Entries": [
        ""
      ]
    },
    {
      "ID": 2000300,
      "Entries": [
        ""
      ]
    },
    {
      "ID": 2001100,
      "Entries": [
        ""
      ]
    },
    {
      "ID": 2010000,
      "Entries": [
        ""
      ]
    },
    {
      "ID": 2020000,
      "Entries": [
        ""
      ]
    },
    {
      "ID": 2030000,
      "Entries": [
        ""
      ]
    },
    {
      "ID": 3000000,
      "Entries": [
        ""
      ]
    },
    {
      "ID": 3000100,
      "Entries": [
        ""
      ]
    },
    {
      "ID": 3000200,
      "Entries": [
        ""
      ]
    },
    {
      "ID": 3000300,
      "Entries": [
        ""
      ]
    },
    {
      "ID": 3001100,
      "Entries": [
        ""
      ]
    },
    {
      "ID": 3010000,
      "Entries": [
        ""
      ]
    },
    {
      "ID": 3010100,
      "Entries": [
        ""
      ]
    },
    {
      "ID": 3010200,
      "Entries": [
        ""
      ]
    },
    {
      "ID": 3010300,
      "Entries": [
        ""
      ]
    },
    {
      "ID": 5000000,
      "Entries": [
        ""
      ]
    },
    {
      "ID": 5000100,
      "Entries": [
        ""
      ]
    },
    {
      "ID": 5000200,
      "Entries": [
        ""
      ]
    },
    {
      "ID": 5000300,
      "Entries": [
        ""
      ]
    },
    {
      "ID": 5002100,
      "Entries": [
        ""
      ]
    },
    {
      "ID": 5010000,
      "Entries": [
        ""
      ]
    },
    {
      "ID": 5010100,
      "Entries": [
        ""
      ]
    },
    {
      "ID": 5010200,
      "Entries": [
        ""
      ]
    },
    {
      "ID": 5010300,
      "Entries": [
        ""
      ]
    },
    {
      "ID": 5020000,
      "Entries": [
        ""
      ]
    },
    {
      "ID": 5020100,
      "Entries": [
        ""
      ]
    },
    {
      "ID": 5020200,
      "Entries": [
        ""
      ]
    },
    {
      "ID": 5020300,
      "Entries": [
        ""
      ]
    },
    {
      "ID": 5021000,
      "Entries": [
        ""
      ]
    },
    {
      "ID": 5030000,
      "Entries": [
        ""
      ]
    },
    {
      "ID": 5030100,
      "Entries": [
        ""
      ]
    },
    {
      "ID": 5030200,
      "Entries": [
        ""
      ]
    },
    {
      "ID": 5030300,
      "Entries": [
        ""
      ]
    },
    {
      "ID": 5031100,
      "Entries": [
        ""
      ]
    },
    {
      "ID": 5032100,
      "Entries": [
        ""
      ]
    },
    {
      "ID": 5040000,
      "Entries": [
        ""
      ]
    },
    {
      "ID": 5040100,
      "Entries": [
        ""
      ]
    },
    {
      "ID": 5040200,
      "Entries": [
        ""
      ]
    },
    {
      "ID": 5040300,
      "Entries": [
        ""
      ]
    },
    {
      "ID": 5050000,
      "Entries": [
        ""
      ]
    },
    {
      "ID": 5050100,
      "Entries": [
        ""
      ]
    },
    {
      "ID": 5050200,
      "Entries": [
        ""
      ]
    },
    {
      "ID": 5050300,
      "Entries": [
        ""
      ]
    },
    {
      "ID": 5060000,
      "Entries": [
        ""
      ]
    },
    {
      "ID": 5060100,
      "Entries": [
        ""
      ]
    },
    {
      "ID": 5060200,
      "Entries": [
        ""
      ]
    },
    {
      "ID": 5060300,
      "Entries": [
        ""
      ]
    },
    {
      "ID": 5062100,
      "Entries": [
        ""
      ]
    },
    {
      "ID": 5070000,
      "Entries": [
        ""
      ]
    },
    {
      "ID": 5070100,
      "Entries": [
        ""
      ]
    },
    {
      "ID": 5070200,
      "Entries": [
        ""
      ]
    },
    {
      "ID": 5070300,
      "Entries": [
        ""
      ]
    },
    {
      "ID": 5080000,
      "Entries": [
        ""
      ]
    },
    {
      "ID": 5080100,
      "Entries": [
        ""
      ]
    },
    {
      "ID": 5080200,
      "Entries": [
        ""
      ]
    },
    {
      "ID": 5080300,
      "Entries": [
        ""
      ]
    },
    {
      "ID": 5081100,
      "Entries": [
        ""
      ]
    },
    {
      "ID": 5090000,
      "Entries": [
        ""
      ]
    },
    {
      "ID": 5090100,
      "Entries": [
        ""
      ]
    },
    {
      "ID": 5090200,
      "Entries": [
        ""
      ]
    },
    {
      "ID": 5090300,
      "Entries": [
        ""
      ]
    },
    {
      "ID": 5100000,
      "Entries": [
        ""
      ]
    },
    {
      "ID": 5100100,
      "Entries": [
        ""
      ]
    },
    {
      "ID": 5100200,
      "Entries": [
        ""
      ]
    },
    {
      "ID": 5100300,
      "Entries": [
        ""
      ]
    },
    {
      "ID": 5101000,
      "Entries": [
        ""
      ]
    },
    {
      "ID": 5101100,
      "Entries": [
        ""
      ]
    },
    {
      "ID": 5102100,
      "Entries": [
        ""
      ]
    },
    {
      "ID": 5102200,
      "Entries": [
        ""
      ]
    },
    {
      "ID": 5102300,
      "Entries": [
        ""
      ]
    },
    {
      "ID": 5110000,
      "Entries": [
        ""
      ]
    },
    {
      "ID": 5110100,
      "Entries": [
        ""
      ]
    },
    {
      "ID": 5110200,
      "Entries": [
        ""
      ]
    },
    {
      "ID": 5110300,
      "Entries": [
        ""
      ]
    },
    {
      "ID": 5111100,
      "Entries": [
        ""
      ]
    },
    {
      "ID": 5120000,
      "Entries": [
        ""
      ]
    },
    {
      "ID": 5120100,
      "Entries": [
        ""
      ]
    },
    {
      "ID": 5120200,
      "Entries": [
        ""
      ]
    },
    {
      "ID": 5120300,
      "Entries": [
        ""
      ]
    },
    {
      "ID": 5121100,
      "Entries": [
        ""
      ]
    },
    {
      "ID": 5122000,
      "Entries": [
        ""
      ]
    },
    {
      "ID": 5130000,
      "Entries": [
        ""
      ]
    },
    {
      "ID": 5130100,
      "Entries": [
        ""
      ]
    },
    {
      "ID": 5130200,
      "Entries": [
        ""
      ]
    },
    {
      "ID": 5130300,
      "Entries": [
        ""
      ]
    },
    {
      "ID": 5131100,
      "Entries": [
        ""
      ]
    },
    {
      "ID": 5140000,
      "Entries": [
        ""
      ]
    },
    {
      "ID": 5140100,
      "Entries": [
        ""
      ]
    },
    {
      "ID": 5140200,
      "Entries": [
        ""
      ]
    },
    {
      "ID": 5140300,
      "Entries": [
        ""
      ]
    },
    {
      "ID": 5141100,
      "Entries": [
        ""
      ]
    },
    {
      "ID": 5150000,
      "Entries": [
        ""
      ]
    },
    {
      "ID": 5150100,
      "Entries": [
        ""
      ]
    },
    {
      "ID": 5150200,
      "Entries": [
        ""
      ]
    },
    {
      "ID": 5150300,
      "Entries": [
        ""
      ]
    },
    {
      "ID": 5160000,
      "Entries": [
        ""
      ]
    },
    {
      "ID": 5160100,
      "Entries": [
        ""
      ]
    },
    {
      "ID": 5160200,
      "Entries": [
        ""
      ]
    },
    {
      "ID": 5160300,
      "Entries": [
        ""
      ]
    },
    {
      "ID": 5170000,
      "Entries": [
        ""
      ]
    },
    {
      "ID": 5170100,
      "Entries": [
        ""
      ]
    },
    {
      "ID": 5170200,
      "Entries": [
        ""
      ]
    },
    {
      "ID": 5170300,
      "Entries": [
        ""
      ]
    },
    {
      "ID": 5172000,
      "Entries": [
        ""
      ]
    },
    {
      "ID": 5172100,
      "Entries": [
        ""
      ]
    },
    {
      "ID": 5172200,
      "Entries": [
        ""
      ]
    },
    {
      "ID": 5172300,
      "Entries": [
        ""
      ]
    },
    {
      "ID": 5180000,
      "Entries": [
        ""
      ]
    },
    {
      "ID": 5180100,
      "Entries": [
        ""
      ]
    },
    {
      "ID": 5180200,
      "Entries": [
        ""
      ]
    },
    {
      "ID": 5180300,
      "Entries": [
        ""
      ]
    },
    {
      "ID": 5181100,
      "Entries": [
        ""
      ]
    },
    {
      "ID": 5182000,
      "Entries": [
        ""
      ]
    },
    {
      "ID": 5183000,
      "Entries": [
        ""
      ]
    },
    {
      "ID": 5184000,
      "Entries": [
        ""
      ]
    },
    {
      "ID": 5190000,
      "Entries": [
        ""
      ]
    },
    {
      "ID": 5190100,
      "Entries": [
        ""
      ]
    },
    {
      "ID": 5190200,
      "Entries": [
        ""
      ]
    },
    {
      "ID": 5190300,
      "Entries": [
        ""
      ]
    },
    {
      "ID": 5191000,
      "Entries": [
        ""
      ]
    },
    {
      "ID": 5191100,
      "Entries": [
        ""
      ]
    },
    {
      "ID": 5200000,
      "Entries": [
        ""
      ]
    },
    {
      "ID": 5200100,
      "Entries": [
        ""
      ]
    },
    {
      "ID": 5200200,
      "Entries": [
        ""
      ]
    },
    {
      "ID": 5200300,
      "Entries": [
        ""
      ]
    },
    {
      "ID": 5210000,
      "Entries": [
        ""
      ]
    },
    {
      "ID": 5210100,
      "Entries": [
        ""
      ]
    },
    {
      "ID": 5210200,
      "Entries": [
        ""
      ]
    },
    {
      "ID": 5210300,
      "Entries": [
        ""
      ]
    },
    {
      "ID": 5220000,
      "Entries": [
        ""
      ]
    },
    {
      "ID": 5220100,
      "Entries": [
        ""
      ]
    },
    {
      "ID": 5220200,
      "Entries": [
        ""
      ]
    },
    {
      "ID": 5220300,
      "Entries": [
        ""
      ]
    },
    {
      "ID": 5221000,
      "Entries": [
        ""
      ]
    },
    {
      "ID": 5230000,
      "Entries": [
        ""
      ]
    },
    {
      "ID": 5230100,
      "Entries": [
        ""
      ]
    },
    {
      "ID": 5230200,
      "Entries": [
        ""
      ]
    },
    {
      "ID": 5230300,
      "Entries": [
        ""
      ]
    },
    {
      "ID": 5231100,
      "Entries": [
        ""
      ]
    },
    {
      "ID": 5240000,
      "Entries": [
        ""
      ]
    },
    {
      "ID": 5240100,
      "Entries": [
        ""
      ]
    },
    {
      "ID": 5240200,
      "Entries": [
        ""
      ]
    },
    {
      "ID": 5240300,
      "Entries": [
        ""
      ]
    },
    {
      "ID": 5250000,
      "Entries": [
        ""
      ]
    },
    {
      "ID": 5250100,
      "Entries": [
        ""
      ]
    },
    {
      "ID": 5250200,
      "Entries": [
        ""
      ]
    },
    {
      "ID": 5250300,
      "Entries": [
        ""
      ]
    },
    {
      "ID": 5252000,
      "Entries": [
        ""
      ]
    },
    {
      "ID": 5252100,
      "Entries": [
        ""
      ]
    },
    {
      "ID": 5253000,
      "Entries": [
        ""
      ]
    },
    {
      "ID": 5253100,
      "Entries": [
        ""
      ]
    },
    {
      "ID": 5253200,
      "Entries": [
        ""
      ]
    },
    {
      "ID": 5253300,
      "Entries": [
        ""
      ]
    },
    {
      "ID": 5260000,
      "Entries": [
        ""
      ]
    },
    {
      "ID": 5260100,
      "Entries": [
        ""
      ]
    },
    {
      "ID": 5260200,
      "Entries": [
        ""
      ]
    },
    {
      "ID": 5260300,
      "Entries": [
        ""
      ]
    },
    {
      "ID": 5270000,
      "Entries": [
        ""
      ]
    },
    {
      "ID": 5270100,
      "Entries": [
        ""
      ]
    },
    {
      "ID": 5270200,
      "Entries": [
        ""
      ]
    },
    {
      "ID": 5270300,
      "Entries": [
        ""
      ]
    },
    {
      "ID": 5271100,
      "Entries": [
        ""
      ]
    },
    {
      "ID": 5272000,
      "Entries": [
        ""
      ]
    },
    {
      "ID": 5280000,
      "Entries": [
        ""
      ]
    },
    {
      "ID": 5280100,
      "Entries": [
        ""
      ]
    },
    {
      "ID": 5280200,
      "Entries": [
        ""
      ]
    },
    {
      "ID": 5280300,
      "Entries": [
        ""
      ]
    },
    {
      "ID": 5290000,
      "Entries": [
        ""
      ]
    },
    {
      "ID": 5300000,
      "Entries": [
        ""
      ]
    },
    {
      "ID": 5310000,
      "Entries": [
        ""
      ]
    },
    {
      "ID": 5320000,
      "Entries": [
        ""
      ]
    },
    {
      "ID": 5330000,
      "Entries": [
        ""
      ]
    },
    {
      "ID": 9999999,
      "Entries": [
        ""
      ]
    }
  ]
}