{
  "Name": "GameAreaParam",
  "Entries": [
    {
      "ID": 0,
      "Entries": [
        ""
      ]
    },
    {
      "ID": 1,
      "Entries": [
        ""
      ]
    },
    {
      "ID": 9999991,
      "Entries": [
        ""
      ]
    },
    {
      "ID": 9999992,
      "Entries": [
        ""
      ]
    },
    {
      "ID": 10000800,
      "Entries": [
        ""
      ]
    },
    {
      "ID": 10000850,
      "Entries": [
        ""
      ]
    },
    {
      "ID": 10010800,
      "Entries": [
        ""
      ]
    },
    {
      "ID": 11000800,
      "Entries": [
        ""
      ]
    },
    {
      "ID": 11000850,
      "Entries": [
        ""
      ]
    },
    {
      "ID": 11050800,
      "Entries": [
        ""
      ]
    },
    {
      "ID": 11050850,
      "Entries": [
        ""
      ]
    },
    {
      "ID": 12010800,
      "Entries": [
        ""
      ]
    },
    {
      "ID": 12010850,
      "Entries": [
        ""
      ]
    },
    {
      "ID": 12020800,
      "Entries": [
        ""
      ]
    },
    {
      "ID": 12020830,
      "Entries": [
        ""
      ]
    },
    {
      "ID": 12020850,
      "Entries": [
        ""
      ]
    },
    {
      "ID": 12030390,
      "Entries": [
        ""
      ]
    },
    {
      "ID": 12030800,
      "Entries": [
        ""
      ]
    },
    {
      "ID": 12030850,
      "Entries": [
        ""
      ]
    },
    {
      "ID": 12040800,
      "Entries": [
        ""
      ]
    },
    {
      "ID": 12050800,
      "Entries": [
        ""
      ]
    },
    {
      "ID": 12080800,
      "Entries": [
        ""
      ]
    },
    {
      "ID": 12090800,
      "Entries": [
        ""
      ]
    },
    {
      "ID": 13000800,
      "Entries": [
        ""
      ]
    },
    {
      "ID": 13000830,
      "Entries": [
        ""
      ]
    },
    {
      "ID": 13000850,
      "Entries": [
        ""
      ]
    },
    {
      "ID": 14000800,
      "Entries": [
        ""
      ]
    },
    {
      "ID": 14000850,
      "Entries": [
        ""
      ]
    },
    {
      "ID": 15000800,
      "Entries": [
        ""
      ]
    },
    {
      "ID": 15000850,
      "Entries": [
        ""
      ]
    },
    {
      "ID": 16000800,
      "Entries": [
        ""
      ]
    },
    {
      "ID": 16000850,
      "Entries": [
        ""
      ]
    },
    {
      "ID": 16000860,
      "Entries": [
        ""
      ]
    },
    {
      "ID": 18000800,
      "Entries": [
        ""
      ]
    },
    {
      "ID": 18000850,
      "Entries": [
        ""
      ]
    },
    {
      "ID": 19000800,
      "Entries": [
        ""
      ]
    },
    {
      "ID": 20000800,
      "Entries": [
        ""
      ]
    },
    {
      "ID": 20010800,
      "Entries": [
        ""
      ]
    },
    {
      "ID": 20010850,
      "Entries": [
        ""
      ]
    },
    {
      "ID": 21000850,
      "Entries": [
        ""
      ]
    },
    {
      "ID": 21010800,
      "Entries": [
        ""
      ]
    },
    {
      "ID": 22000800,
      "Entries": [
        ""
      ]
    },
    {
      "ID": 25000800,
      "Entries": [
        ""
      ]
    },
    {
      "ID": 28000800,
      "Entries": [
        ""
      ]
    },
    {
      "ID": 30000800,
      "Entries": [
        ""
      ]
    },
    {
      "ID": 30010800,
      "Entries": [
        ""
      ]
    },
    {
      "ID": 30020800,
      "Entries": [
        ""
      ]
    },
    {
      "ID": 30030800,
      "Entries": [
        ""
      ]
    },
    {
      "ID": 30040800,
      "Entries": [
        ""
      ]
    },
    {
      "ID": 30050800,
      "Entries": [
        ""
      ]
    },
    {
      "ID": 30050850,
      "Entries": [
        ""
      ]
    },
    {
      "ID": 30060800,
      "Entries": [
        ""
      ]
    },
    {
      "ID": 30070800,
      "Entries": [
        ""
      ]
    },
    {
      "ID": 30080800,
      "Entries": [
        ""
      ]
    },
    {
      "ID": 30090800,
      "Entries": [
        ""
      ]
    },
    {
      "ID": 30100800,
      "Entries": [
        ""
      ]
    },
    {
      "ID": 30100801,
      "Entries": [
        ""
      ]
    },
    {
      "ID": 30110800,
      "Entries": [
        ""
      ]
    },
    {
      "ID": 30120800,
      "Entries": [
        ""
      ]
    },
    {
      "ID": 30120801,
      "Entries": [
        ""
      ]
    },
    {
      "ID": 30130800,
      "Entries": [
        ""
      ]
    },
    {
      "ID": 30140800,
      "Entries": [
        ""
      ]
    },
    {
      "ID": 30150800,
      "Entries": [
        ""
      ]
    },
    {
      "ID": 30160800,
      "Entries": [
        ""
      ]
    },
    {
      "ID": 30170800,
      "Entries": [
        ""
      ]
    },
    {
      "ID": 30180800,
      "Entries": [
        ""
      ]
    },
    {
      "ID": 30190800,
      "Entries": [
        ""
      ]
    },
    {
      "ID": 30200800,
      "Entries": [
        ""
      ]
    },
    {
      "ID": 31000800,
      "Entries": [
        ""
      ]
    },
    {
      "ID": 31010800,
      "Entries": [
        ""
      ]
    },
    {
      "ID": 31020800,
      "Entries": [
        ""
      ]
    },
    {
      "ID": 31030800,
      "Entries": [
        ""
      ]
    },
    {
      "ID": 31040800,
      "Entries": [
        ""
      ]
    },
    {
      "ID": 31050800,
      "Entries": [
        ""
      ]
    },
    {
      "ID": 31060800,
      "Entries": [
        ""
      ]
    },
    {
      "ID": 31070800,
      "Entries": [
        ""
      ]
    },
    {
      "ID": 31090800,
      "Entries": [
        ""
      ]
    },
    {
      "ID": 31100800,
      "Entries": [
        ""
      ]
    },
    {
      "ID": 31110800,
      "Entries": [
        ""
      ]
    },
    {
      "ID": 31120800,
      "Entries": [
        ""
      ]
    },
    {
      "ID": 31150800,
      "Entries": [
        ""
      ]
    },
    {
      "ID": 31170800,
      "Entries": [
        ""
      ]
    },
    {
      "ID": 31180800,
      "Entries": [
        ""
      ]
    },
    {
      "ID": 31190800,
      "Entries": [
        ""
      ]
    },
    {
      "ID": 31190850,
      "Entries": [
        ""
      ]
    },
    {
      "ID": 31200800,
      "Entries": [
        ""
      ]
    },
    {
      "ID": 31210800,
      "Entries": [
        ""
      ]
    },
    {
      "ID": 31220800,
      "Entries": [
        ""
      ]
    },
    {
      "ID": 32000800,
      "Entries": [
        ""
      ]
    },
    {
      "ID": 32010800,
      "Entries": [
        ""
      ]
    },
    {
      "ID": 32020800,
      "Entries": [
        ""
      ]
    },
    {
      "ID": 32040800,
      "Entries": [
        ""
      ]
    },
    {
      "ID": 32050800,
      "Entries": [
        ""
      ]
    },
    {
      "ID": 32050801,
      "Entries": [
        ""
      ]
    },
    {
      "ID": 32070800,
      "Entries": [
        ""
      ]
    },
    {
      "ID": 32080800,
      "Entries": [
        ""
      ]
    },
    {
      "ID": 32110800,
      "Entries": [
        ""
      ]
    },
    {
      "ID": 34120800,
      "Entries": [
        ""
      ]
    },
    {
      "ID": 34130800,
      "Entries": [
        ""
      ]
    },
    {
      "ID": 34140850,
      "Entries": [
        ""
      ]
    },
    {
      "ID": 35000800,
      "Entries": [
        ""
      ]
    },
    {
      "ID": 35000850,
      "Entries": [
        ""
      ]
    },
    {
      "ID": 39200800,
      "Entries": [
        ""
      ]
    },
    {
      "ID": 40000800,
      "Entries": [
        ""
      ]
    },
    {
      "ID": 40010800,
      "Entries": [
        ""
      ]
    },
    {
      "ID": 41000800,
      "Entries": [
        ""
      ]
    },
    {
      "ID": 41010800,
      "Entries": [
        ""
      ]
    },
    {
      "ID": 41020800,
      "Entries": [
        ""
      ]
    },
    {
      "ID": 43000800,
      "Entries": [
        ""
      ]
    },
    {
      "ID": 43010800,
      "Entries": [
        ""
      ]
    },
    {
      "ID": 1033420800,
      "Entries": [
        ""
      ]
    },
    {
      "ID": 1033430800,
      "Entries": [
        ""
      ]
    },
    {
      "ID": 1033450800,
      "Entries": [
        ""
      ]
    },
    {
      "ID": 1034420800,
      "Entries": [
        ""
      ]
    },
    {
      "ID": 1034450800,
      "Entries": [
        ""
      ]
    },
    {
      "ID": 1034480800,
      "Entries": [
        ""
      ]
    },
    {
      "ID": 1034500800,
      "Entries": [
        ""
      ]
    },
    {
      "ID": 1035420800,
      "Entries": [
        ""
      ]
    },
    {
      "ID": 1035500800,
      "Entries": [
        ""
      ]
    },
    {
      "ID": 1035530800,
      "Entries": [
        ""
      ]
    },
    {
      "ID": 1036450340,
      "Entries": [
        ""
      ]
    },
    {
      "ID": 1036480340,
      "Entries": [
        ""
      ]
    },
    {
      "ID": 1036500800,
      "Entries": [
        ""
      ]
    },
    {
      "ID": 1036540800,
      "Entries": [
        ""
      ]
    },
    {
      "ID": 1037420340,
      "Entries": [
        ""
      ]
    },
    {
      "ID": 1037460800,
      "Entries": [
        ""
      ]
    },
    {
      "ID": 1037510800,
      "Entries": [
        ""
      ]
    },
    {
      "ID": 1037530800,
      "Entries": [
        ""
      ]
    },
    {
      "ID": 1037540810,
      "Entries": [
        ""
      ]
    },
    {
      "ID": 1038410800,
      "Entries": [
        ""
      ]
    },
    {
      "ID": 1038480800,
      "Entries": [
        ""
      ]
    },
    {
      "ID": 1038510800,
      "Entries": [
        ""
      ]
    },
    {
      "ID": 1038520340,
      "Entries": [
        ""
      ]
    },
    {
      "ID": 1039430340,
      "Entries": [
        ""
      ]
    },
    {
      "ID": 1039440800,
      "Entries": [
        ""
      ]
    },
    {
      "ID": 1039500800,
      "Entries": [
        ""
      ]
    },
    {
      "ID": 1039510800,
      "Entries": [
        ""
      ]
    },
    {
      "ID": 1039540800,
      "Entries": [
        ""
      ]
    },
    {
      "ID": 1040520800,
      "Entries": [
        ""
      ]
    },
    {
      "ID": 1040530800,
      "Entries": [
        ""
      ]
    },
    {
      "ID": 1041500800,
      "Entries": [
        ""
      ]
    },
    {
      "ID": 1041510800,
      "Entries": [
        ""
      ]
    },
    {
      "ID": 1041520800,
      "Entries": [
        ""
      ]
    },
    {
      "ID": 1041530800,
      "Entries": [
        ""
      ]
    },
    {
      "ID": 1042330800,
      "Entries": [
        ""
      ]
    },
    {
      "ID": 1042360800,
      "Entries": [
        ""
      ]
    },
    {
      "ID": 1042370800,
      "Entries": [
        ""
      ]
    },
    {
      "ID": 1042380800,
      "Entries": [
        ""
      ]
    },
    {
      "ID": 1042380850,
      "Entries": [
        ""
      ]
    },
    {
      "ID": 1042550800,
      "Entries": [
        ""
      ]
    },
    {
      "ID": 1043300800,
      "Entries": [
        ""
      ]
    },
    {
      "ID": 1043330800,
      "Entries": [
        ""
      ]
    },
    {
      "ID": 1043360800,
      "Entries": [
        ""
      ]
    },
    {
      "ID": 1043370340,
      "Entries": [
        ""
      ]
    },
    {
      "ID": 1043530800,
      "Entries": [
        ""
      ]
    },
    {
      "ID": 1044320340,
      "Entries": [
        ""
      ]
    },
    {
      "ID": 1044320342,
      "Entries": [
        ""
      ]
    },
    {
      "ID": 1044350800,
      "Entries": [
        ""
      ]
    },
    {
      "ID": 1044360800,
      "Entries": [
        ""
      ]
    },
    {
      "ID": 1044530800,
      "Entries": [
        ""
      ]
    },
    {
      "ID": 1045390800,
      "Entries": [
        ""
      ]
    },
    {
      "ID": 1045520800,
      "Entries": [
        ""
      ]
    },
    {
      "ID": 1047400800,
      "Entries": [
        ""
      ]
    },
    {
      "ID": 1048370800,
      "Entries": [
        ""
      ]
    },
    {
      "ID": 1048400800,
      "Entries": [
        ""
      ]
    },
    {
      "ID": 1048410800,
      "Entries": [
        ""
      ]
    },
    {
      "ID": 1048510800,
      "Entries": [
        ""
      ]
    },
    {
      "ID": 1048570800,
      "Entries": [
        ""
      ]
    },
    {
      "ID": 1049370800,
      "Entries": [
        ""
      ]
    },
    {
      "ID": 1049370850,
      "Entries": [
        ""
      ]
    },
    {
      "ID": 1049380800,
      "Entries": [
        ""
      ]
    },
    {
      "ID": 1049390800,
      "Entries": [
        ""
      ]
    },
    {
      "ID": 1049390850,
      "Entries": [
        ""
      ]
    },
    {
      "ID": 1049520800,
      "Entries": [
        ""
      ]
    },
    {
      "ID": 1050560800,
      "Entries": [
        ""
      ]
    },
    {
      "ID": 1050570800,
      "Entries": [
        ""
      ]
    },
    {
      "ID": 1050570850,
      "Entries": [
        ""
      ]
    },
    {
      "ID": 1051360800,
      "Entries": [
        ""
      ]
    },
    {
      "ID": 1051400800,
      "Entries": [
        ""
      ]
    },
    {
      "ID": 1051430800,
      "Entries": [
        ""
      ]
    },
    {
      "ID": 1051570800,
      "Entries": [
        ""
      ]
    },
    {
      "ID": 1052380800,
      "Entries": [
        ""
      ]
    },
    {
      "ID": 1052410800,
      "Entries": [
        ""
      ]
    },
    {
      "ID": 1052410850,
      "Entries": [
        ""
      ]
    },
    {
      "ID": 1052520800,
      "Entries": [
        ""
      ]
    },
    {
      "ID": 1052560800,
      "Entries": [
        ""
      ]
    },
    {
      "ID": 1053560800,
      "Entries": [
        ""
      ]
    },
    {
      "ID": 1054560800,
      "Entries": [
        ""
      ]
    },
    {
      "ID": 1248550800,
      "Entries": [
        ""
      ]
    },
    {
      "ID": 2044450800,
      "Entries": [
        ""
      ]
    },
    {
      "ID": 2044470800,
      "Entries": [
        ""
      ]
    },
    {
      "ID": 2045440800,
      "Entries": [
        ""
      ]
    },
    {
      "ID": 2046380800,
      "Entries": [
        ""
      ]
    },
    {
      "ID": 2046400800,
      "Entries": [
        ""
      ]
    },
    {
      "ID": 2046410800,
      "Entries": [
        ""
      ]
    },
    {
      "ID": 2046450800,
      "Entries": [
        ""
      ]
    },
    {
      "ID": 2046460800,
      "Entries": [
        ""
      ]
    },
    {
      "ID": 2047390800,
      "Entries": [
        ""
      ]
    },
    {
      "ID": 2047450800,
      "Entries": [
        ""
      ]
    },
    {
      "ID": 2048380850,
      "Entries": [
        ""
      ]
    },
    {
      "ID": 2048440800,
      "Entries": [
        ""
      ]
    },
    {
      "ID": 2049410800,
      "Entries": [
        ""
      ]
    },
    {
      "ID": 2049430800,
      "Entries": [
        ""
      ]
    },
    {
      "ID": 2049430850,
      "Entries": [
        ""
      ]
    },
    {
      "ID": 2049450800,
      "Entries": [
        ""
      ]
    },
    {
      "ID": 2049480800,
      "Entries": [
        ""
      ]
    },
    {
      "ID": 2050470800,
      "Entries": [
        ""
      ]
    },
    {
      "ID": 2050480800,
      "Entries": [
        ""
      ]
    },
    {
      "ID": 2050480860,
      "Entries": [
        ""
      ]
    },
    {
      "ID": 2051440800,
      "Entries": [
        ""
      ]
    },
    {
      "ID": 2051450720,
      "Entries": [
        ""
      ]
    },
    {
      "ID": 2052400800,
      "Entries": [
        ""
      ]
    },
    {
      "ID": 2052430800,
      "Entries": [
        ""
      ]
    },
    {
      "ID": 2052480800,
      "Entries": [
        ""
      ]
    },
    {
      "ID": 2054390800,
      "Entries": [
        ""
      ]
    },
    {
      "ID": 2054390850,
      "Entries": [
        ""
      ]
    }
  ]
}